neatpush/__init__.py
neatpush/__main__.py
neatpush/app.py
neatpush/config.py
neatpush/manga.py
neatpush/scraping.py
neatpush-0.3.1.dist-info/METADATA
neatpush-0.3.1.dist-info/WHEEL
neatpush-0.3.1.dist-info/entry_points.txt
neatpush-0.3.1.dist-info/licenses/LICENSE
neatpush-0.3.1.dist-info/RECORD
